odoo/addons/stock_intercompany_bidirectional/README.rst
odoo/addons/stock_intercompany_bidirectional/__init__.py
odoo/addons/stock_intercompany_bidirectional/__manifest__.py
odoo/addons/stock_intercompany_bidirectional/data/demo_data.xml
odoo/addons/stock_intercompany_bidirectional/i18n/it.po
odoo/addons/stock_intercompany_bidirectional/i18n/stock_intercompany_bidirectional.pot
odoo/addons/stock_intercompany_bidirectional/models/__init__.py
odoo/addons/stock_intercompany_bidirectional/models/res_company.py
odoo/addons/stock_intercompany_bidirectional/models/res_config_settings.py
odoo/addons/stock_intercompany_bidirectional/models/stock_picking.py
odoo/addons/stock_intercompany_bidirectional/readme/CONFIGURE.rst
odoo/addons/stock_intercompany_bidirectional/readme/CONTEXT.rst
odoo/addons/stock_intercompany_bidirectional/readme/CONTRIBUTORS.rst
odoo/addons/stock_intercompany_bidirectional/readme/DESCRIPTION.rst
odoo/addons/stock_intercompany_bidirectional/readme/USAGE.rst
odoo/addons/stock_intercompany_bidirectional/static/description/icon.png
odoo/addons/stock_intercompany_bidirectional/static/description/icon.svg
odoo/addons/stock_intercompany_bidirectional/static/description/index.html
odoo/addons/stock_intercompany_bidirectional/tests/__init__.py
odoo/addons/stock_intercompany_bidirectional/tests/test_intercompany_bidirectional_picking.py
odoo/addons/stock_intercompany_bidirectional/views/res_config_settings.xml
odoo_addon_stock_intercompany_bidirectional-16.0.1.0.3.dist-info/METADATA
odoo_addon_stock_intercompany_bidirectional-16.0.1.0.3.dist-info/WHEEL
odoo_addon_stock_intercompany_bidirectional-16.0.1.0.3.dist-info/top_level.txt
odoo_addon_stock_intercompany_bidirectional-16.0.1.0.3.dist-info/RECORD
