Metadata-Version: 2.1
Name: odoo-addon-stock_intercompany_bidirectional
Version: 16.0.1.0.3
Summary: Bidirectional operations for the Stock Intercomany module
Home-page: https://github.com/OCA/multi-company
Author: Cetmix, Odoo Community Association (OCA)
Author-email: support@odoo-community.org
License: AGPL-3
Classifier: Programming Language :: Python
Classifier: Framework :: Odoo
Classifier: Framework :: Odoo :: 16.0
Classifier: License :: OSI Approved :: GNU Affero General Public License v3
Requires-Python: >=3.10
Requires-Dist: odoo-addon-stock-intercompany<16.1dev,>=16.0dev
Requires-Dist: odoo<16.1dev,>=16.0a
